odoo/addons/stock_move_location/README.rst
odoo/addons/stock_move_location/__init__.py
odoo/addons/stock_move_location/__manifest__.py
odoo/addons/stock_move_location/data/stock_quant_view.xml
odoo/addons/stock_move_location/i18n/de.po
odoo/addons/stock_move_location/i18n/es.po
odoo/addons/stock_move_location/i18n/stock_move_location.pot
odoo/addons/stock_move_location/models/__init__.py
odoo/addons/stock_move_location/models/stock_move.py
odoo/addons/stock_move_location/models/stock_picking_type.py
odoo/addons/stock_move_location/readme/CONTRIBUTORS.rst
odoo/addons/stock_move_location/readme/DESCRIPTION.rst
odoo/addons/stock_move_location/readme/ROADMAP.rst
odoo/addons/stock_move_location/readme/USAGE.rst
odoo/addons/stock_move_location/static/description/icon.png
odoo/addons/stock_move_location/static/description/index.html
odoo/addons/stock_move_location/tests/__init__.py
odoo/addons/stock_move_location/tests/test_common.py
odoo/addons/stock_move_location/tests/test_move_location.py
odoo/addons/stock_move_location/views/stock_picking_type_views.xml
odoo/addons/stock_move_location/wizard/__init__.py
odoo/addons/stock_move_location/wizard/stock_move_location.py
odoo/addons/stock_move_location/wizard/stock_move_location.xml
odoo/addons/stock_move_location/wizard/stock_move_location_line.py
odoo11_addon_stock_move_location-11.0.2.1.0.dist-info/METADATA
odoo11_addon_stock_move_location-11.0.2.1.0.dist-info/WHEEL
odoo11_addon_stock_move_location-11.0.2.1.0.dist-info/top_level.txt
odoo11_addon_stock_move_location-11.0.2.1.0.dist-info/RECORD
