Metadata-Version: 2.1
Name: odoo11-addon-stock-move-location
Version: 11.0.2.1.0
Summary: This module allows to move all stock in a stock location to an other one.
Home-page: https://github.com/OCA/stock-logistics-warehouse
Author: Julius Network Solutions, Odoo Community Association (OCA)
Author-email: support@odoo-community.org
License: AGPL-3
Platform: UNKNOWN
Classifier: Programming Language :: Python
Classifier: Framework :: Odoo
Classifier: License :: OSI Approved :: GNU Affero General Public License v3
Requires-Python: >=2.7, !=3.0.*, !=3.1.*, !=3.2.*, !=3.3.*, !=3.4.*
Requires-Dist: odoo (<11.1dev,>=11.0a)
